batdetect2_view/__init__.py
batdetect2_view/batdetect2_view.py
batdetect2_view/cli.py
batdetect2_view/consolidate_detections.py
batdetect2_view/create_visualization.py
batdetect2_view-1.4.1.dist-info/licenses/LICENSE
batdetect2_view-1.4.1.dist-info/METADATA
batdetect2_view-1.4.1.dist-info/WHEEL
batdetect2_view-1.4.1.dist-info/entry_points.txt
batdetect2_view-1.4.1.dist-info/top_level.txt
batdetect2_view-1.4.1.dist-info/RECORD
