Metadata-Version: 2.4
Name: batdetect2-view
Version: 1.4.1
Summary: A visualization tool for batdetect2 output files
Author: Niall
License-Expression: MIT
Classifier: Programming Language :: Python :: 3
Classifier: Operating System :: OS Independent
Requires-Python: >=3.6
License-File: LICENSE
Requires-Dist: argparse
Dynamic: license-file
